pvtpy/__init__.py
pvtpy/black_oil/__init__.py
pvtpy/black_oil/__pvt.py
pvtpy/black_oil/correlations.py
pvtpy/compositional/__init__.py
pvtpy/compositional/chromatography.py
pvtpy/compositional/components.py
pvtpy/compositional/components_properties1.csv
pvtpy/compositional/correlations.py
pvtpy/compositional/equations.py
pvtpy/compositional/separators.py
pvtpy/eos/__init__.py
pvtpy/eos/peng_robinson.py
pvtpy/eos/redlich_kwong.py
pvtpy/eos/soave_redlich_kwong.py
pvtpy/eos/van_der_walls.py
pvtpy/fluids/__init__.py
pvtpy/fluids/base.py
pvtpy/fluids/gas.py
pvtpy/fluids/oil.py
pvtpy/fluids/water.py
pvtpy/pvt/__init__.py
pvtpy/pvt/pvt.py
pvtpy/units/__init__.py
pvtpy/units/units.py
pvtpy-0.1.4.dist-info/LICENSE
pvtpy-0.1.4.dist-info/METADATA
pvtpy-0.1.4.dist-info/WHEEL
pvtpy-0.1.4.dist-info/RECORD
